xrdPlanner/__init__.py
xrdPlanner/classes.py
xrdPlanner/resources.py
xrdPlanner/run_xrdPlanner.py
xrdPlanner-2023.6.21.dist-info/LICENSE
xrdPlanner-2023.6.21.dist-info/METADATA
xrdPlanner-2023.6.21.dist-info/WHEEL
xrdPlanner-2023.6.21.dist-info/entry_points.txt
xrdPlanner-2023.6.21.dist-info/top_level.txt
xrdPlanner-2023.6.21.dist-info/RECORD
