Metadata-Version: 2.1
Name: xrdPlanner
Version: 2023.6.21
Summary: A tool to project X-ray diffraction cones on a detector screen at different geometries (tilt, rotation, offset) and X-ray energies.
Home-page: https://github.com/LennardKrause/xrdPlanner/
Author: Lennard Krause
Author-email: lkrause@chem.au.dk
License: GNU GENERAL PUBLIC LICENSE
Classifier: Development Status :: 5 - Production/Stable
Classifier: Intended Audience :: Science/Research
Classifier: License :: OSI Approved :: GNU General Public License (GPL)
Classifier: Topic :: Education
Classifier: Topic :: Scientific/Engineering
Classifier: Operating System :: OS Independent
License-File: LICENSE
Requires-Dist: numpy (>=1.24)
Requires-Dist: pyqtgraph (>=0.13)
Requires-Dist: Dans-Diffraction (>=2.2.3)
Requires-Dist: PyQt6 (>=6.5)
Requires-Dist: pyFAI (>=2023.5)
